LICENSE
README.rst
setup.cfg
setup.py
docs/changelog.rst
docs/code_of_conduct.md
docs/contributing.md
src/senaite/__init__.py
src/senaite.diagnosis.egg-info/PKG-INFO
src/senaite.diagnosis.egg-info/SOURCES.txt
src/senaite.diagnosis.egg-info/dependency_links.txt
src/senaite.diagnosis.egg-info/entry_points.txt
src/senaite.diagnosis.egg-info/namespace_packages.txt
src/senaite.diagnosis.egg-info/not-zip-safe
src/senaite.diagnosis.egg-info/requires.txt
src/senaite.diagnosis.egg-info/top_level.txt
src/senaite/diagnosis/__init__.py
src/senaite/diagnosis/config.py
src/senaite/diagnosis/configure.zcml
src/senaite/diagnosis/interfaces.py
src/senaite/diagnosis/permissions.py
src/senaite/diagnosis/permissions.zcml
src/senaite/diagnosis/setuphandlers.py
src/senaite/diagnosis/utils.py
src/senaite/diagnosis/browser/__init__.py
src/senaite/diagnosis/browser/configure.zcml
src/senaite/diagnosis/browser/content/__init__.py
src/senaite/diagnosis/browser/content/configure.zcml
src/senaite/diagnosis/browser/content/diseases.py
src/senaite/diagnosis/browser/content/etiologicagents.py
src/senaite/diagnosis/browser/content/symptoms.py
src/senaite/diagnosis/browser/static/assets/icons/disease.svg
src/senaite/diagnosis/browser/static/assets/icons/etiologic_agent.svg
src/senaite/diagnosis/browser/static/assets/icons/symptom.svg
src/senaite/diagnosis/browser/theme/__init__.py
src/senaite/diagnosis/browser/theme/configure.zcml
src/senaite/diagnosis/browser/theme/icons.py
src/senaite/diagnosis/content/__init__.py
src/senaite/diagnosis/content/analysisrequest.py
src/senaite/diagnosis/content/configure.zcml
src/senaite/diagnosis/content/disease.py
src/senaite/diagnosis/content/diseases.py
src/senaite/diagnosis/content/etiologicagent.py
src/senaite/diagnosis/content/etiologicagents.py
src/senaite/diagnosis/content/fields.py
src/senaite/diagnosis/content/symptom.py
src/senaite/diagnosis/content/symptoms.py
src/senaite/diagnosis/locales/senaite.diagnosis.pot
src/senaite/diagnosis/locales/ca/LC_MESSAGES/senaite.diagnosis.po
src/senaite/diagnosis/locales/de/LC_MESSAGES/senaite.diagnosis.po
src/senaite/diagnosis/locales/en/LC_MESSAGES/senaite.diagnosis.po
src/senaite/diagnosis/locales/es/LC_MESSAGES/senaite.diagnosis.po
src/senaite/diagnosis/locales/zh/LC_MESSAGES/senaite.diagnosis.po
src/senaite/diagnosis/locales/zh_CN/LC_MESSAGES/senaite.diagnosis.po
